{"country_code":"RW","country_name":"Rwanda","source":"Field research + Wikidata","count":6,"orgs":[{"n":"Rwanda Civil Society Network","d":"Primary civil society network in Rwanda","w":""},{"n":"National Cooperatives Confederation of Rwanda (NCCR)","d":"800x600 Normal 0 false false false EN-GB X-NONE X-NONE MicrosoftInternetExplorer4 st1:*{behavior:url(#ieooui) } /* Style Definitions */ table.MsoNormalTable {mso-style-name:\"Table Normal\"; mso-tstyle-","w":"https://www.nccr.coop.rw"},{"n":"Association for Co-Operation and Research in Development","d":"research institute in Rwanda","w":"https://acordrwanda.org/"},{"n":"Centrale des Syndicats des Travailleurs du Rwanda","d":"ITUC affiliate. CESTRAR. 72,000 members.","w":""},{"n":"Confédération des Travailleurs du Secteur Privé","d":"ITUC affiliate. CTSP.","w":""},{"n":"Congrès du Travail et de la Fraternité au Rwanda","d":"ITUC affiliate. COTRAF. 20,000 members.","w":""}]}