{"state":"NJ","name":"New Jersey","count":232,"orgs":[{"n":"COOPER HEALTH SYSTEM A NEW JERSEY NON-PROFIT CORPORATION","c":"CAMDEN","t":"E22","w":"","r":2550029191},{"n":"COMMUNITY FOOD BANK OF NEW JERSEY INC","c":"HILLSIDE","t":"K31Z","w":"","r":214145989},{"n":"COOPER UNIVERSITY HOSPITAL CAPE REGIONAL INC","c":"CAPE MAY CH","t":"E220","w":"","r":145351448},{"n":"NEWARK COMMUNITY HEALTH CENTERS INC","c":"NEWARK","t":"E32Z","w":"","r":40859367},{"n":"OCEAN MENTAL HEALTH SERVICES INC","c":"BAYVILLE","t":"F320","w":"","r":32039903},{"n":"MENTAL HEALTH ASSOCIATION OF ESSEX AND MORRIS INC","c":"MONTCLAIR","t":"F80Z","w":"","r":23060042},{"n":"EDUCATION & HEALTH CENTERS OF AMERICA INC","c":"WALL TOWNSHIP","t":"F40Z","w":"","r":20536768},{"n":"SOUTHERN NEW JERSEY PERINATAL COOPERATIVE","c":"PENNSAUKEN","t":"E46Z","w":"","r":19215924},{"n":"COOPER HEALTH SYSTEMS","c":"CAMDEN","t":"E11","w":"","r":12500224},{"n":"NORTHWEST ESSEX COMMUNITY HEALTHCARE NETWORK INC","c":"BELLEVILLE","t":"F32","w":"","r":11191277},{"n":"AFFORDABLE HOUSING ALLIANCE INC","c":"NEPTUNE","t":"L80","w":"","r":9460662},{"n":"NEW COMMUNITY HEALTH CARE INC","c":"NEWARK","t":"E320","w":"","r":8904705},{"n":"HEALTHCARE BUSINESSWOMENS ASSOCIATION INC","c":"FAIRFIELD","t":"S41","w":"","r":8462160},{"n":"COMMUNITY HEALTH LAW PROJECT","c":"SOUTH ORANGE","t":"E00K","w":"","r":7883577},{"n":"INTERFAITH FOOD PANTRY INC","c":"MORRIS PLAINS","t":"K31","w":"","r":7723538},{"n":"DISABILITY RIGHTS NEW JERSEY A NEW JERSEY NONPROFIT CORPORATION","c":"TRENTON","t":"I83","w":"","r":5460220},{"n":"FOOD BANK OF SOMERSET COUNTY INC","c":"BOUND BROOK","t":"K31Z","w":"","r":5239262},{"n":"HIGH PARK GARDENS COOPERATIVE CORP","c":"NEWARK","t":"L21","w":"","r":4644057},{"n":"SPARTA COMMUNITY FOOD PANTRY INC","c":"SPARTA","t":"K31","w":"","r":4357943},{"n":"HOUSING AND COMMUNITY DEVELOPMENT NETWORK OF NEW JERSEY INC","c":"TRENTON","t":"L20Z","w":"","r":3287830},{"n":"SALVATION AND SOCIAL JUSTICE","c":"TRENTON","t":"R22","w":"","r":2997615},{"n":"NATIONAL WOMENS HEALTH RESOURCE CENTER INC","c":"MIDDLETOWN","t":"E701","w":"","r":2849932},{"n":"HABITAT FOR HUMANITY INTERNATIONAL INC","c":"NEWARK","t":"L20Z","w":"","r":2827611},{"n":"EAST BRUNSWICK COMMUNITY HOUSING CORPORATION INC","c":"E BRUNSWICK","t":"L20Z","w":"","r":2435672},{"n":"NEW JERSEY LEAGUE OF CONSERVATION VOTERS EDUCATION FUND","c":"TRENTON","t":"C013","w":"","r":2423783},{"n":"HEALTH RESEARCH & EDUCATIONAL TRUST OF NEW JERSEY","c":"PRINCETON","t":"E00B","w":"","r":2405465},{"n":"COOPERATIVE BUSINESS ASSISTANCE CORPORATION","c":"CAMDEN","t":"S43Z","w":"","r":2115500},{"n":"NEW JERSEY ASSOCIATION FOR JUSTICE EDUCATIONAL FOUNDATION INC","c":"TRENTON","t":"I99Z","w":"","r":2098798},{"n":"FORESIGHT AFFORDABLE HOUSING OF PENNSYLVANIA INC","c":"EGG HBR TWP","t":"L210","w":"","r":2045691},{"n":"INTERFAITH FOOD PANTRY OF THE ORANGES INC","c":"SHORT HILLS","t":"K31","w":"","r":1933960},{"n":"GRANDVIEW APARTMENTS AFFORDABLE HOUSING CORPORATION","c":"NEPTUNE","t":"L210","w":"","r":1838148},{"n":"PRINCETON HOUSING AND COMMUNITY DEVELOPMENT CORPORATION","c":"PRINCETON","t":"L21","w":"","r":1742999},{"n":"URBAN AGRICULTURE COOPERATIVE","c":"NEWARK","t":"K02","w":"","r":1740933},{"n":"PARTNERS FOR WOMEN AND JUSTICE INC","c":"BLOOMFIELD","t":"I80","w":"","r":1544061},{"n":"BRADLEY FOOD PANTRY INC","c":"NEPTUNE CITY","t":"K31","w":"","r":1537324},{"n":"NEW COMMUNITY HUDSON SENIOR HOUSING CORPORATION","c":"NEWARK","t":"L220","w":"","r":1466180},{"n":"COOPER UNIVERSITY HEALTH CAPE REGIONAL INC","c":"CAPE MAY CH","t":"E21","w":"","r":1434851},{"n":"NEW JERSEY ENVIRONMENTAL JUSTICE ALLIANCE INC","c":"NEWARK","t":"C01","w":"","r":1288707},{"n":"OPEN CUPBOARD FOOD PANTRY INC","c":"CLINTON","t":"K31","w":"","r":1273887},{"n":"MENTAL HEALTH ASSOCIATION IN PASSAIC","c":"CLIFTON","t":"F80Z","w":"","r":1264124},{"n":"AFFORDABLE HOUSING CORPORATION OF GLASSBORO","c":"GLASSBORO","t":"L21","w":"","r":1178284},{"n":"FERNBROOK ENVIRONMENTAL EDUCATION CENTER INC","c":"CHESTERFIELD","t":"C99","w":"","r":1172074},{"n":"EDUCATION HEALTH AND RESEARCH INTERNATIONAL INC","c":"BRICK","t":"E70","w":"","r":1158641},{"n":"PENWAL AFFORDABLE HOUSING CORPORATION","c":"RIDGEWOOD","t":"L210","w":"","r":1005355},{"n":"URBAN LEAGUE AFFORDABLE HOUSING AND COMMUNITY DEVELOPMENTAL CORPOR","c":"JERSEY CITY","t":"L80Z","w":"","r":888102},{"n":"UNITED COMMUNITY URBAN HOUSING CORPORATION","c":"NEWARK","t":"W99","w":"","r":784140},{"n":"COMMUNITY HOUSING RESOURCE BOARD OF SOUTHERN BERGEN COUNTY INC","c":"HACKENSACK","t":"L21Z","w":"","r":770637},{"n":"WECARE ALLIANCE FOR MENTAL HEALTH INC","c":"PERTH AMBOY","t":"F30","w":"","r":761858},{"n":"CHERRY HILL FREE CLINIC INC","c":"CHERRY HILL","t":"E32","w":"","r":760769},{"n":"GREATER CULVER LAKE WATERSHED CONSERVATION FOUNDATION","c":"BRANCHVILLE","t":"C32","w":"","r":758267},{"n":"COOPERATIVE HOUSING CORPORATION","c":"SOMERVILLE","t":"L20Z","w":"","r":741014},{"n":"NEW JERSEY FARMERS COOPERATIVE","c":"WEST CAPE MAY","t":"K20","w":"","r":694842},{"n":"PASSAIC AFFORDABLE HOUSING COALITION","c":"PASSAIC","t":"L20","w":"","r":691109},{"n":"HABITAT FOR HUMANITY INTERNATIONAL INC","c":"CARNEYS POINT","t":"L20Z","w":"","r":649788},{"n":"LONG HILL TOWNSHIP COMMUNITY HOUSING DEVELOPMENT CORP","c":"STIRLING","t":"L22Z","w":"","r":620968},{"n":"BERGEN COUNTY COMMUNITY HOUSING IN PARTNERSHIP INC","c":"HACKENSACK","t":"L20Z","w":"","r":590437},{"n":"PRINCETON COMMUNITY HOUSING INC","c":"PRINCETON","t":"L52Z","w":"","r":576797},{"n":"COALITION FOR FOOD AND HEALTH EQUITY INC","c":"JERSEY CITY","t":"E01","w":"","r":486542},{"n":"NEIGHBORHOOD AFFORDABLE HOUSING FRIENDS INC","c":"EDGEWATER","t":"L99","w":"","r":482453},{"n":"L & T AFFORDABLE HOUSING URBAN RENEWAL CORPORATION","c":"CLIFFSIDE PARK","t":"L40","w":"","r":440090},{"n":"AMERICAN EAGLE FOOD PANTRY OF NORTHERN NEW JERSEY","c":"LODI","t":"K31","w":"","r":345944},{"n":"MERCY COOP & CAFE A NJ NONPROFIT CORPORATION","c":"JERSEY CITY","t":"K30","w":"","r":339626},{"n":"HIGHLAND PARK AFFORDABLE HOUSING CORPORATION","c":"HIGHLAND PARK","t":"L40","w":"","r":332612},{"n":"BAYARD RUSTIN CENTER FOR SOCIAL JUSTICE","c":"PRINCETON","t":"R99","w":"","r":325629},{"n":"INNOVATIVE DIGESTIVE HEALTH EDUCATION AND RESEARCH INC","c":"NEW BRUNSWICK","t":"E70","w":"","r":308154},{"n":"DELAWARE VALLEY FOOD PANTRY INC","c":"LAMBERTVILLE","t":"K30","w":"","r":304210},{"n":"LACEY FOOD BANK INC","c":"FORKED RIVER","t":"K31","w":"","r":286560},{"n":"MENTAL HEALTH INSTITUTE OF NEW JERSEY","c":"FRANKLIN LKS","t":"F60","w":"","r":280091},{"n":"EAST ORANGE HOUSING AND COMMUNITY DEVELOPMENT CORPORATION","c":"EAST ORANGE","t":"L20","w":"","r":237095},{"n":"BETTER COMMUNITY HOUSING OF TRENTON INC","c":"TRENTON","t":"L20","w":"","r":195192},{"n":"BESSIE MAE WOMENS HEALTH CENTER","c":"EAST ORANGE","t":"E32","w":"","r":193113},{"n":"ESSEX COMMUNITY LAND TRUST INC","c":"EAST ORANGE","t":"L80","w":"","r":189690},{"n":"WOMEN IN ENERGY INC","c":"SCOTCH PLAINS","t":"J03","w":"","r":176643},{"n":"MUTUAL AID EMERGENCY SERVICES","c":"ABSECON","t":"E62","w":"","r":165697},{"n":"TRI-BORO FOOD PANTRY","c":"PARK RIDGE","t":"K31","w":"","r":163727},{"n":"MORRIS COUNTY AFFORDABLE HOUSING CORPORATION","c":"MORRISTOWN","t":"L20","w":"","r":149683},{"n":"ST LUKE COMMUNITY AND HEALTH SERVICE","c":"BELLEVILLE","t":"F30","w":"","r":144424},{"n":"FOOD BANK NEWS INC","c":"MAPLEWOOD","t":"K31","w":"","r":138155},{"n":"NEW JERSEY ENVIRONMENTAL HEALTH ASSOCIATION","c":"FREEHOLD","t":"S41","w":"","r":131968},{"n":"AFFORDABLE HOUSING OF METROPOLITAN EDGEWATER INC","c":"EDGEWATER","t":"L21","w":"","r":117118},{"n":"SOCIETY OF WOMEN ENVIRONMENTAL PROFESSIONALS","c":"NEW PROVIDNCE","t":"S41","w":"","r":116786},{"n":"WEST BERGEN HOUSING FOR MENTAL HEALTH","c":"RIDGEWOOD","t":"F33Z","w":"","r":115557},{"n":"NEIGHBORHOOD COLLABORATIVE COMMUNITY GARDENS","c":"CAMDEN","t":"C50","w":"","r":114261},{"n":"CENTER FOR EDUCATION AND JUVENILE JUSTICE","c":"NEWARK","t":"I21","w":"","r":93492},{"n":"HELPING HAND FOOD PANTRY","c":"HILLSDALE","t":"K30","w":"","r":91153},{"n":"WOODBRIDGE AFFORDABLE HOUSING CORP","c":"WOODBRIDGE","t":"L20","w":"","r":90129},{"n":"KEYPORT MINISTERIUM FOOD PANTRY INC","c":"KEYPORT","t":"K31","w":"","r":84655},{"n":"MENTAL HEALTH ASSOCIATION FOUNDATION INC","c":"TINTON FALLS","t":"F99","w":"","r":77959},{"n":"JUSTICE HOUSING INC","c":"BELMAR","t":"L21","w":"","r":76894},{"n":"EDISON AFFORDABLE HOUSING INC","c":"EDISON","t":"L20","w":"","r":76643},{"n":"HEALTH EMPLOYEES ALLIANCE RIGHTS & TRADES LOCAL 707 INC","c":"SOUTH ORANGE","t":"J40","w":"","r":63315},{"n":"WILDERMAN FUND FOR MATERNAL MENTAL HEALTH","c":"TENAFLY","t":"F60","w":"","r":54849},{"n":"LOAVES AND FISHES COMMUNITY FOOD PANTRY INC","c":"BOONTON","t":"K31","w":"","r":49142},{"n":"WESTFIELD FOOD PANTRY","c":"WESTFIELD","t":"K31","w":"","r":33768},{"n":"BERGEN COUNTY COMMUNITY HEALTH IMPROVEMENT PARTNERSHIP","c":"HACKENSACK","t":"E70","w":"","r":32657},{"n":"BRICK HOUSING AND COMMUNITY DEVELOPMENT CORPORATION","c":"BRICK","t":"L22","w":"","r":31447},{"n":"COUNSELING & EDUCATION CENTER FOR ASIAN-AMERICAN WOMEN INC","c":"METUCHEN","t":"F60","w":"","r":29873},{"n":"WINEMAKERS CO-OP INC","c":"PITTSTOWN","t":"K2A","w":"","r":19877},{"n":"FRIENDS OF CLEMENTON FOOD PANTRY INC","c":"CLEMENTON","t":"K31","w":"","r":18289},{"n":"AFFORDABLE HOUSING OPPORTUNITIES MATTER INC","c":"BOONTON","t":"L02","w":"","r":16036},{"n":"RED BANK AFFORDABLE HOUSING CORPORATION","c":"RED BANK","t":"L21","w":"","r":12654},{"n":"NEW JERSEY MENTAL HEALTH INSTITUTE INC","c":"MERCERVILLE","t":"F02","w":"","r":12090},{"n":"ETHNIC COMMUNITY-BASED ORGANIZATION FOR REFUGEES AND IMMIGRANTS","c":"LAMBERTVILLE","t":"S21","w":"","r":10250},{"n":"WINANS ST COMMUNITY GARDEN","c":"VERONA","t":"K30","w":"","r":2217},{"n":"AFFORDABLE HOUSING ALTERNATIVES OF GLOUCESTER COUNTY INC","c":"DEPTFORD","t":"L20","w":"","r":15},{"n":"AACC FOOD PANTRY INC","c":"ATLANTIC HLDS","t":"K31","w":"","r":0},{"n":"ABCO FEDERAL CREDIT UNION FOUNDATION INC","c":"MOORESTOWN","t":"W61","w":"","r":0},{"n":"AFFORDABLE HOUSING CORP OF LAKEWOOD","c":"LAKEWOOD","t":"L20","w":"","r":0},{"n":"AFFORDABLE HOUSING CORPORATION OF VINELAND","c":"VINELAND","t":"L82","w":"","r":0},{"n":"AFFORDABLE HOUSING PROFESSIONALS OFNEW JERSEY INC","c":"PRINCETON","t":"S46","w":"","r":0},{"n":"ANTI-RACIST MENTAL HEALTH ALLIANCE-NJ INC","c":"NEWARK","t":"F01","w":"","r":0},{"n":"BARNEGAT COMMUNITY GARDEN INC","c":"BARNEGAT","t":"C42","w":"","r":0},{"n":"BARNEGAT FOOD PANTRY INC","c":"BARNEGAT","t":"K31","w":"","r":0},{"n":"BERKELEY TOWNSHIP AFFORDABLE HOUSING CORPORATION","c":"BAYVILLE","t":"L19","w":"","r":0},{"n":"CARPATHIA COMMUNITY HOUSING CORP","c":"PARSIPPANY","t":"L21","w":"","r":0},{"n":"CEDAR PLACE FOOD BANK AND COMMUNITY OUTREACH","c":"PENNSAUKEN","t":"K31","w":"","r":0},{"n":"CENTER FOR ARTS AND VISUAL EDUCATION INC","c":"LYNDHURST","t":"J22","w":"","r":0},{"n":"CENTER FOR WETLAND ADVOCATION CONSERVATION AND EDUCATION","c":"PT PLEASANT","t":"C60","w":"","r":0},{"n":"CHESTER MENDHAM FOOD PANTRY A NEW JERSEY NONPROFIT CORPORATION","c":"CHESTER","t":"K31","w":"","r":0},{"n":"CLOSTER FOOD PANTRY INC","c":"CLOSTER","t":"K31","w":"","r":0},{"n":"COLLINGSWOOD FOOD PANTRY INC","c":"MICKLETON","t":"K31","w":"","r":0},{"n":"COMMUNITY DEVELOPMENT AND HOUSING R ESOURCE CENTER OF NEW JERSEY","c":"BERLIN","t":"S99","w":"","r":0},{"n":"COMMUNITY EDUCATIONAL SUPPORT ENTERPRISES","c":"SWEDESBORO","t":"S20","w":"","r":0},{"n":"COOPER HEALTH SYSTEMS","c":"CAMDEN","t":"E11","w":"","r":0},{"n":"COOPER HEALTH SYSTEMS","c":"CAMDEN","t":"E11","w":"","r":0},{"n":"COOPER HEALTH SYSTEMS","c":"CAMDEN","t":"E11","w":"","r":0},{"n":"COOPER HEALTH SYSTEMS","c":"CAMDEN","t":"E11","w":"","r":0},{"n":"COOPER HEALTH SYSTEMS","c":"CAMDEN","t":"E11","w":"","r":0},{"n":"COOPER-CHANDLER COMMUNITY OUTREACH CENTER A NJ NONPROFIT CORPORATION","c":"NEW BRUNSWICK","t":"S20","w":"","r":0},{"n":"COOPERATIVE HOME HEALTH CARE OF ATLANTIC COUNTY INC","c":"EGG HBR TWP","t":"E92","w":"","r":0},{"n":"CW COMMUNITY FOOD PANTRY AND RESOURCE CENTER","c":"ATLANTIC CITY","t":"K31","w":"","r":0},{"n":"Cooperative Housing Corporation","c":"Somerville","t":"L20Z","w":"","r":0},{"n":"EGYPTIAN AMERICAN FOR DEMOCRACY & HUMAN RIGHTS NY-NJ CORP","c":"CLIFTON","t":"R30","w":"","r":0},{"n":"ENVIRONMENTAL AND GLOBAL COMMUNITY AID","c":"HIGHLANDS","t":"W99","w":"","r":0},{"n":"ENVIRONMENTAL EDUCATION FUND","c":"TRENTON","t":"C30","w":"","r":0},{"n":"ESHIN AFFORDABLE HOUSING CORPORATION","c":"SUMMIT","t":"L99","w":"","r":0},{"n":"ETOWN HOUSING AND COMMUNITY DEVELOPMENT CORPORATION","c":"ELIZABETH","t":"L21","w":"","r":0},{"n":"EVERYONE FOR ACCESSIBLE COMMUNITY HOUSING ROLLS INC","c":"CLINTON","t":"L01","w":"","r":0},{"n":"EXPERT AFFORDABLE HOUSING FOUNDATION","c":"MOUNT LAUREL","t":"L21","w":"","r":0},{"n":"East Bergen Firefighters Mutual Aid Association","c":"Palisades Pk","t":"P60","w":"","r":0},{"n":"Environmental Justice & Equity With Community Based Teamwork Eject Inc","c":"Atlantic Hlds","t":"C20","w":"","r":0},{"n":"Essex Community Land Trust Inc","c":"East Orange","t":"L80","w":"","r":0},{"n":"FOOD JUSTICE FOR ALL","c":"WEEHAWKEN","t":"L12","w":"","r":0},{"n":"FREE VACCINE FOR ALL COMMUNITY HEALTH CLINIC","c":"HILLSBOROUGH","t":"E70","w":"","r":0},{"n":"FRIENDS OF THE MONROE TOWNSHIP COMMUNITY GARDEN","c":"MONROE TWP","t":"C42","w":"","r":0},{"n":"GARDEN STATE FOOD DISTRIBUTOR","c":"CAMDEN","t":"K31","w":"","r":0},{"n":"GARDEN STATE OIL & ENERGY PROFESSIONALS INC","c":"BOONTON","t":"S41","w":"","r":0},{"n":"GARDEN STATE SEAFOOD ASSOCIATION","c":"CAPE MAY","t":"S46","w":"","r":0},{"n":"GARDEN STATE UAW HOUSING CORP INC","c":"NEW BRUNSWICK","t":"L21","w":"","r":0},{"n":"GLOBAL FOREST COOPERATIVE","c":"LAMBERTVILLE","t":"C36","w":"","r":0},{"n":"GOOD DEEDS FOOD PANTRY","c":"NEW BRUNSWICK","t":"W12","w":"","r":0},{"n":"GREEN ACRE COMMUNITY GARDEN A NJ NONPROFIT CORPORATION","c":"PATERSON","t":"S19","w":"","r":0},{"n":"HACKENSACK AFFORDABLE HOUSING URBAN RENEWAL CORPORATION","c":"CLIFFSIDE PARK","t":"L21","w":"","r":0},{"n":"HANDS OF GRACE FOOD PANTRY","c":"PASSAIC","t":"K31","w":"","r":0},{"n":"HARRIETS VISION OF COMMUNITY UNITY AND EDUCATION","c":"COLUMBUS","t":"R99","w":"","r":0},{"n":"HEALTH AND EDUCATION FOUNDATION INC","c":"UNION","t":"F21","w":"","r":0},{"n":"HEAVENS HELPERS FOOD PANTRY & SOUP KITCHEN","c":"WOODBRIDGE","t":"K30","w":"","r":0},{"n":"HILLSIDE VICTORY COMMUNITY GARDEN CLUB","c":"HILLSIDE","t":"C42","w":"","r":0},{"n":"HOPE HAPPENS HERE MENTAL HEALTH AWARENESS FOUNDATION","c":"HAWTHORNE","t":"F80","w":"","r":0},{"n":"HOUSING & COMMUNITY DEVELOPMENT NETWORK ACTION FUND","c":"HAMILTON","t":"L20","w":"","r":0},{"n":"HOUSING 4 VETERANS MEN & WOMEN FOR OTHERS","c":"HOBOKEN","t":"L01","w":"","r":0},{"n":"HOWELL EMERGENCY FOOD PANTRY INC","c":"HOWELL","t":"K31Z","w":"","r":0},{"n":"HOWELL ORGANIC COMMUNITY GARDENS A NJ NONPROFIT CORPORATION","c":"FARMINGDALE","t":"K11","w":"","r":0},{"n":"HUNTERDON REGIONAL COMMUNITY HEALTH INC","c":"FLEMINGTON","t":"E21","w":"","r":0},{"n":"INSTITUTE OF RESEARCH FOR SOCIAL JUSTICE IN ACTION INC","c":"EAST ORANGE","t":"I01","w":"","r":0},{"n":"INTERNATIONAL CENTER FOR AGROECOLOGY","c":"MONMOUTH JCT","t":"K05","w":"","r":0},{"n":"INTERNATIONAL INSTITUTE FOR SOCIAL JUSTICE","c":"SOUTH ORANGE","t":"R20","w":"","r":0},{"n":"ISLAMIC COMMUNITY HEALTH COLLABORATIVE","c":"NEWARK","t":"E60","w":"","r":0},{"n":"ISLAMIC COOPERATIVE","c":"NEWARK","t":"S20","w":"","r":0},{"n":"ITALIAN AMERICAN CIVIL RIGHTS LEAGUE NP","c":"LYNDHURST","t":"R99","w":"","r":0},{"n":"International Center For Agroecology","c":"Monmouth Jct","t":"K05","w":"","r":0},{"n":"JERSEY CITY AFFORDABLE HOUSING COALITION","c":"JERSEY CITY","t":"S31","w":"","r":0},{"n":"JUSTICE EDUCATION PROJECT A NJ NONPROFIT CORPORATION","c":"WARREN","t":"R01","w":"","r":0},{"n":"KEARNY COMMUNITY FOOD PANTRY","c":"KEARNY","t":"K31","w":"","r":0},{"n":"LAWRENCE TOWNSHIP ENVIRONMENTAL EDUCATION FOUNDATION INC","c":"LAWRENCE TWP","t":"C340","w":"","r":0},{"n":"LEAGUE FOR SOCIAL JUSTICE","c":"HILLSIDE","t":"R99","w":"","r":0},{"n":"LETS TALK WOMENS HEALTH & WELLNESS A NJ NONPROFIT CORPORATION","c":"JERSEY CITY","t":"E70","w":"","r":0},{"n":"LIV AFFORDABLE HOUSING INC","c":"LAKEWOOD","t":"L20","w":"","r":0},{"n":"MANDAEAN HUMAN RIGHTS GROUP","c":"MORRISTOWN","t":"R20","w":"","r":0},{"n":"MAVEN COMMUNITY HEALTH INC","c":"MORRIS PLAINS","t":"E32","w":"","r":0},{"n":"MENTAL HEALTHCARE SOLUTION INCORPORATED","c":"BYRAM TWP","t":"F60","w":"","r":0},{"n":"MIDDLESEX COMMUNITY HEALTH CENTER INC","c":"SOUTH AMBOY","t":"E70","w":"","r":0},{"n":"MONTCLAIR MUTUAL AID","c":"MONTCLAIR","t":"K31","w":"","r":0},{"n":"MOVE FOR MENTAL HEALTH INC","c":"MOUNT LAUREL","t":"F01","w":"","r":0},{"n":"MT CALVARY FOOD BANK","c":"ELIZABETH","t":"K31","w":"","r":0},{"n":"Montclair Mutual Aid","c":"Montclair","t":"K31","w":"","r":0},{"n":"Mutual Aid Emergency Services","c":"Absecon","t":"E62","w":"","r":0},{"n":"NATIONAL CENTER FOR ENVIRONMENTAL HEALTH STRATEGIES INC","c":"VOORHEES","t":"C60Z","w":"","r":0},{"n":"NEIGHBORHOOD REDEVELOPMENT COOPERATIVE SOLUTIONS","c":"PERTH AMBOY","t":"S20","w":"","r":0},{"n":"NEW JERSEY AFFORDABLE HOUSING CORPORATION","c":"TRENTON","t":"L21","w":"","r":0},{"n":"NEW JERSEY ASSOCIATION FOR INFANT MENTAL HEALTH INC","c":"UPR MONTCLAIR","t":"F30","w":"","r":0},{"n":"NEW JERSEY BLACK MAYORS ALLIANCE FOR SOCIAL JUSTICE INC","c":"NEWARK","t":"S80","w":"","r":0},{"n":"NEW JERSEY CHAPTER OF THE SOCIETY FOR PUBLIC HEALTH EDUCATION INC","c":"BERGENFIELD","t":"E30","w":"","r":0},{"n":"NEW JERSEY WOMENS AFFORDABLE HOUSING NETWORK","c":"GLEN RIDGE","t":"L03","w":"","r":0},{"n":"NEW LIFE FOOD PANTRY","c":"HELMETTA","t":"K31","w":"","r":0},{"n":"NEW MARGARET HAGUE WOMENS HEALTH INSTITUTE","c":"OCEANPORT","t":"E31Z","w":"","r":0},{"n":"NEW PAULUS HOOK COMMUNITY HOUSING CORP","c":"PARSIPPANY","t":"S47","w":"","r":0},{"n":"NEW YORK WOMENS AFFORDABLE HOUSING NETWORK","c":"WESTFIELD","t":"S03","w":"","r":0},{"n":"NEWARK AFFORDABLE HOUSING COALITION","c":"WEST ORANGE","t":"L20","w":"","r":0},{"n":"NIGERIAN MENTAL HEALTH PRACTITIONERS USA INC","c":"MILLVILLE","t":"F03","w":"","r":0},{"n":"NON-PROFIT FOUNDATION FOR AFFORDABLE HOUSING CORP","c":"EDISON","t":"L21","w":"","r":0},{"n":"NORTH BRUNSWICK FOOD BANK INC","c":"N BRUNSWICK","t":"K31Z","w":"","r":0},{"n":"NORTH JERSEY BLACK CAUCUS FOR SOCIAL JUSTICE INC","c":"ENGLEWD CLFS","t":"R22","w":"","r":0},{"n":"NORTH STREET FOOD PANTRY","c":"JERSEY CITY","t":"K30","w":"","r":0},{"n":"New Jersey Environmental Justice Alliance Inc","c":"Newark","t":"C01","w":"","r":0},{"n":"Njsangjo Mutual Aid Inc","c":"Palisades Park","t":"","w":"","r":0},{"n":"ONE WORLD WOMENS HEALTH INC","c":"LITTLE SILVER","t":"E12","w":"","r":0},{"n":"OPEN SPACE CONSERVATION COOPERATIVE","c":"FREEHOLD","t":"C30","w":"","r":0},{"n":"OUR DAILY BREAD FOOD PANTRY INC","c":"WHHITING","t":"K31","w":"","r":0},{"n":"PALMYRA COVE ENVIRONMENTAL EDUCATION FOUNDATION INCORPORATED","c":"PALMYRA","t":"C115","w":"","r":0},{"n":"PRINCETON SCHOOL GARDENS COOPERATIVE","c":"PRINCETON","t":"C40","w":"","r":0},{"n":"PROJECTS FOR ENVIRONMENTAL HEALTH KNOWLEDGE & ACTION","c":"LAKEWOOD","t":"C60","w":"","r":0},{"n":"RIDGECREST AFFORDABLE HOUSING A NJ NONPROFIT CORPORATION","c":"RIDGEWOOD","t":"L22","w":"","r":0},{"n":"RIVERVIEW COMMUNITY GARDEN A NJ NONPROFIT CORPORATION","c":"JERSEY CITY","t":"C42","w":"","r":0},{"n":"ROBIN L CROWLEY MEMORIAL FOOD PANTRY INC","c":"EAST ORANGE","t":"K31","w":"","r":0},{"n":"ROUND VALLEY TROUT ASSOCIATION ENVIRONMENTAL CONSERVATION FUND","c":"BLOOMSBURY","t":"C32","w":"","r":0},{"n":"SERV COMMUNITY HOUSING DEVELOPMENT ORGANIZATION A NJ NON-PROFIT CORPO","c":"EWING","t":"L20","w":"","r":0},{"n":"SHIFA COOPERATIVE OF PHYSICIANS AND EMPLOYEES INC","c":"JERSEY CITY","t":"W12","w":"","r":0},{"n":"SHORE COMMUNITY LAND TRUST INC","c":"TOMS RIVER","t":"L20","w":"","r":0},{"n":"SOCIAL JUSTICE MATTERS INC","c":"SCOTCH PLAINS","t":"R30","w":"","r":0},{"n":"SOMERVILLE ALLIANCE FOR FOOD EDUCATION","c":"SOMERVILLE","t":"K99","w":"","r":0},{"n":"SOUTH ASIAN MENTAL HEALTH INITIATIVE AND NETWORK","c":"EDISON","t":"F80","w":"","r":0},{"n":"ST BRIGIDS FOOD PANTRY AND KITCHEN","c":"LONG BRANCH","t":"K31","w":"","r":0},{"n":"STONEHURST AFFORDABLE HOUSING INC","c":"TINTON FALLS","t":"L20","w":"","r":0},{"n":"SUMMIT AFFORDABLE HOUSING CORPORATION","c":"SUMMIT","t":"L20","w":"","r":0},{"n":"Stevens Cooperative School","c":"Hoboken","t":"","w":"","r":0},{"n":"THE EDUCATIONAL AND TRAINING FUND OF THE WOMENS POLITICAL CAUCUS OF","c":"UNION","t":"W24","w":"","r":0},{"n":"THRIVE MENTAL HEALTH & WELLNESS CENTER INC","c":"LAWNSIDE","t":"F22","w":"","r":0},{"n":"TRI-COUNTY COMMUNITY FOOD PANTRY","c":"PENNSVILLE","t":"K12","w":"","r":0},{"n":"WDYTYR WOMEN DAUGHTERS AND YOUTH MINISTRIES INC","c":"JERSEY CITY","t":"W99","w":"","r":0,"d":" [FILTERED: out of scope]"},{"n":"WOMENS HEALTH & LONGEVITY FOUNDATION INC","c":"MANASQUAN","t":"E05","w":"","r":0},{"n":"WRANGLE BROOK COMMUNITY GARDEN","c":"TOMS RIVER","t":"C42","w":"","r":0}]}